{
    "string":[
        {
            "name":"ohos_id_notification_increase_volume_tittle",
            "value":"Creșteți volumul peste nivelul de siguranță?",
            "attr":{
                "priority":"translate"
            }
        },
        {
            "name":"ohos_id_notification_increase_volume_context",
            "value":"Ascultarea la volum ridicat pentru perioade lungi de timp vă poate afecta auzul.",
            "attr":{
                "priority":"translate"
            }
        },
        {
            "name":"ohos_id_notification_restore_volume_button",
            "value":"Restabilire volum",
            "attr":{
                "priority":"translate"
            }
        },
        {
            "name":"ohos_id_notification_restore_volume_context",
            "value":"Ascultarea la volum ridicat pentru perioade lungi de timp vă poate afecta auzul.",
            "attr":{
                "priority":"translate"
            }
        },
        {
            "name":"ohos_id_notification_restore_volume_tittle",
            "value":"Volum redus automat",
            "attr":{
                "priority":"translate"
            }
        },
        {
            "name":"ohos_id_notification_increase_volume_button",
            "value":"Creștere volum",
            "attr":{
                "priority":"translate"
            }
        },
        {
            "name":"request_agent_upload_success",
            "value":"Încărcare reușită",
            "attr":{
                "priority":"translate"
            }
        },
        {
            "name":"request_agent_upload_fail",
            "value":"Încărcare eșuată",
            "attr":{
                "priority":"translate"
            }
        },
        {
            "name":"request_agent_download_fail",
            "value":"Descărcare eșuată",
            "attr":{
                "priority":"translate"
            }
        },
        {
            "name":"request_agent_download_success",
            "value":"Descărcare reușită",
            "attr":{
                "priority":"translate"
            }
        },
        {
            "name":"ohos_id_text_save_button_description_save_image",
            "value":"Salvare imagine",
            "attr":{
                "priority":"translate"
            }
        },
        {
            "name":"save_button_description_save_all",
            "value":"Salvare toate",
            "attr":{
                "priority":"translate"
            }
        },
        {
            "name":"ohos_id_text_save_button_description_download",
            "value":"Descărcare",
            "attr":{
                "priority":"translate"
            }
        },
        {
            "name":"ohos_id_text_save_button_description_receive",
            "value":"Salvare",
            "attr":{
                "priority":"translate"
            }
        },
        {
            "name":"ohos_id_text_save_button_description_save_to_gallery",
            "value":"Salvare în Galerie",
            "attr":{
                "priority":"translate"
            }
        },
        {
            "name":"save_button_description_quick_save_to_gallery",
            "value":"Salvare în Galerie",
            "attr":{
                "priority":"translate"
            }
        },
        {
            "name":"ohos_id_text_save_button_description_download_file",
            "value":"Descărcare fișier",
            "attr":{
                "priority":"translate"
            }
        },
        {
            "name":"ohos_id_text_save_button_description_save",
            "value":"Salvare",
            "attr":{
                "priority":"translate"
            }
        },
        {
            "name":"save_button_description_quick_resave_to_gallery",
            "value":"Salvare",
            "attr":{
                "priority":"translate"
            }
        },
        {
            "name":"ohos_id_text_save_button_description_save_file",
            "value":"Salvare fișier",
            "attr":{
                "priority":"translate"
            }
        },
        {
            "name":"ohos_id_text_paste_button_description_paste",
            "value":"Lipire",
            "attr":{
                "priority":"translate"
            }
        },
        {
            "name":"ohos_id_text_save_button_description_download_and_share",
            "value":"Descărcare și partajare",
            "attr":{
                "priority":"translate"
            }
        },
        {
            "name":"ohos_id_text_save_button_description_continue_to_receive",
            "value":"Salvare",
            "attr":{
                "priority":"translate"
            }
        },
        {
            "name":"save_button_description_export_to_gallery",
            "value":"Exportare",
            "attr":{
                "priority":"translate"
            }
        },
        {
            "name": "prev_arrow_accessibility_text",
            "value": "Înapoi",
            "attr": {
                "priority": "translate"
            }
        },
        {
            "name": "next_arrow_accessibility_text",
            "value": "Înainte",
            "attr": {
                "priority": "translate"
            }
        },
        {
            "name": "general_copy",
            "value": "Copiere",
            "attr": {
                "priority": "translate"
            }
        },
        {
            "name": "general_start",
            "value": "Start",
            "attr": {
                "priority": "translate"
            }
        },
        {
            "name": "general_more",
            "value": "Mai multe",
            "attr": {
                "priority": "translate"
            }
        },
        {
            "name": "navigation_back",
            "value": "Înapoi",
            "attr": {
                "priority": "translate"
            }
        },
        {
            "name": "general_cancel",
            "value": "Anulare",
            "attr": {
                "priority": "translate"
            }
        },
        {
            "name": "general_display_lunar_calendar",
            "value": "Afișare calendar lunar",
            "attr": {
                "priority": "translate"
            }
        },
        {
            "name": "sheet_close",
            "value": "Închidere",
            "attr": {
                "priority": "translate"
            }
        },
        {
            "name": "general_select_all",
            "value": "Selectare toate",
            "attr": {
                "priority": "translate"
            }
        },
        {
            "name": "stepper_back",
            "value": "Înapoi",
            "attr": {
                "priority": "translate"
            }
        },
        {
            "name": "general_cut",
            "value": "Decupare",
            "attr": {
                "priority": "translate"
            }
        },
        {
            "name": "general_confirm",
            "value": "OK",
            "attr": {
                "priority": "translate"
            }
        },
        {
            "name": "general_skip",
            "value": "Omitere",
            "attr": {
                "priority": "translate"
            }
        },
        {
            "name": "last_updated_time",
            "value": "Ultima actualizare: %s",
            "attr": {
                "priority": "translate"
            }
        },
        {
            "name": "general_close",
            "value": "Oprit",
            "attr": {
                "priority": "translate"
            }
        },
        {
            "name": "general_paste",
            "value": "Lipire",
            "attr": {
                "priority": "translate"
            }
        },
        {
            "name": "general_open",
            "value": "Pornit",
            "attr": {
                "priority": "translate"
            }
        },
        {
            "name": "stepper_next",
            "value": "Înainte",
            "attr": {
                "priority": "translate"
            }
        },
        {
            "name":"request_agent_task_count",
            "value":"Reușite: %1$d, Eşuate: %2$d",
            "attr":{
                "priority":"translate"
            }
        },
        {
            "name":"request_agent_download_complete",
            "value":"Descărcare finalizată (%s)",
            "attr":{
                "priority":"translate"
            }
        }
    ]
}
