{
    "string":[
        {
            "name":"ohos_id_notification_increase_volume_tittle",
            "value":"Vill du öka volymen över säker nivå?",
            "attr":{
                "priority":"translate"
            }
        },
        {
            "name":"ohos_id_notification_increase_volume_context",
            "value":"Att lyssna på hög volym under lång tid kan skada din hörsel.",
            "attr":{
                "priority":"translate"
            }
        },
        {
            "name":"ohos_id_notification_restore_volume_button",
            "value":"Återställ volymen",
            "attr":{
                "priority":"translate"
            }
        },
        {
            "name":"ohos_id_notification_restore_volume_context",
            "value":"Att lyssna på hög volym under lång tid kan skada din hörsel.",
            "attr":{
                "priority":"translate"
            }
        },
        {
            "name":"ohos_id_notification_restore_volume_tittle",
            "value":"Volymen sänktes automatiskt",
            "attr":{
                "priority":"translate"
            }
        },
        {
            "name":"ohos_id_notification_increase_volume_button",
            "value":"Höj volymen",
            "attr":{
                "priority":"translate"
            }
        }
    ]
}