{
    "string": [
        {
            "name": "ohos_id_sheet_type",
            "value": "popup"
        },
        {
            "name": "ohos_show_password_directly",
            "value": "1"
        },
        {
            "name": "ohos_id_menu_has_filter",
            "value": "false"
        },
        {
            "name": "ohos_id_calendar_picker_dialog_button_transparent",
            "value": "false"
        },
        {
            "name": "ohos_id_calendar_picker_dialog_divider_transparent",
            "value": "true"
        },
        {
            "name": "menu_normal_layout",
            "value": "0"
        },
        {
            "name": "menu_normal_placement",
            "value": "0"
        },
        {
            "name": "menu_back_blur",
            "value": "0"
        },
        {
            "name": "menu_focus_directional_key_enable_default",
            "value": "1"
        },
        {
            "name": "ohos_id_menu_double_border_enable_default",
            "value": "1"
        },
        {
            "name": "ohos_id_popup_double_border_enable_default",
            "value": "1"
        },
        {
            "name": "res_menu_translate_is_support",
            "value": "1"
        },
        {
            "name": "res_menu_search_is_support",
            "value": "1"
        }
    ]  
}
