{
    "string":[
        {
            "name":"ohos_id_notification_increase_volume_tittle",
            "value":"Aumentar o volume acima do nível de segurança?",
            "attr":{
                "priority":"translate"
            }
        },
        {
            "name":"ohos_id_notification_increase_volume_context",
            "value":"A exposição prolongada a volumes altos pode prejudicar a audição.",
            "attr":{
                "priority":"translate"
            }
        },
        {
            "name":"ohos_id_notification_restore_volume_button",
            "value":"Restaurar o volume",
            "attr":{
                "priority":"translate"
            }
        },
        {
            "name":"ohos_id_notification_restore_volume_context",
            "value":"A exposição prolongada a volumes altos pode prejudicar a audição.",
            "attr":{
                "priority":"translate"
            }
        },
        {
            "name":"ohos_id_notification_restore_volume_tittle",
            "value":"Volume baixado automaticamente",
            "attr":{
                "priority":"translate"
            }
        },
        {
            "name":"ohos_id_notification_increase_volume_button",
            "value":"Aumentar volume",
            "attr":{
                "priority":"translate"
            }
        },
        {
            "name":"request_agent_upload_success",
            "value":"Carregado",
            "attr":{
                "priority":"translate"
            }
        },
        {
            "name":"request_agent_upload_fail",
            "value":"Falha ao carregar",
            "attr":{
                "priority":"translate"
            }
        },
        {
            "name":"request_agent_download_fail",
            "value":"Falha ao transferir",
            "attr":{
                "priority":"translate"
            }
        },
        {
            "name":"request_agent_download_success",
            "value":"Transferido",
            "attr":{
                "priority":"translate"
            }
        },
        {
            "name":"ohos_id_text_save_button_description_save_image",
            "value":"Guardar imagem",
            "attr":{
                "priority":"translate"
            }
        },
        {
            "name":"save_button_description_save_all",
            "value":"Guardar tudo",
            "attr":{
                "priority":"translate"
            }
        },
        {
            "name":"ohos_id_text_save_button_description_download",
            "value":"Transferir",
            "attr":{
                "priority":"translate"
            }
        },
        {
            "name":"ohos_id_text_save_button_description_receive",
            "value":"Guardar",
            "attr":{
                "priority":"translate"
            }
        },
        {
            "name":"ohos_id_text_save_button_description_save_to_gallery",
            "value":"Guardar na Galeria",
            "attr":{
                "priority":"translate"
            }
        },
        {
            "name":"save_button_description_quick_save_to_gallery",
            "value":"Guardar na Galeria",
            "attr":{
                "priority":"translate"
            }
        },
        {
            "name":"ohos_id_text_save_button_description_download_file",
            "value":"Transferir ficheiro",
            "attr":{
                "priority":"translate"
            }
        },
        {
            "name":"ohos_id_text_save_button_description_save",
            "value":"Guardar",
            "attr":{
                "priority":"translate"
            }
        },
        {
            "name":"save_button_description_quick_resave_to_gallery",
            "value":"Guardar",
            "attr":{
                "priority":"translate"
            }
        },
        {
            "name":"ohos_id_text_save_button_description_save_file",
            "value":"Guardar ficheiro",
            "attr":{
                "priority":"translate"
            }
        },
        {
            "name":"ohos_id_text_paste_button_description_paste",
            "value":"Colar",
            "attr":{
                "priority":"translate"
            }
        },
        {
            "name":"ohos_id_text_save_button_description_download_and_share",
            "value":"Transferir e partilhar",
            "attr":{
                "priority":"translate"
            }
        },
        {
            "name":"ohos_id_text_save_button_description_continue_to_receive",
            "value":"Guardar",
            "attr":{
                "priority":"translate"
            }
        },
        {
            "name":"save_button_description_export_to_gallery",
            "value":"Exportar",
            "attr":{
                "priority":"translate"
            }
        },
        {
            "name": "prev_arrow_accessibility_text",
            "value": "Anterior",
            "attr": {
                "priority": "translate"
            }
        },
        {
            "name": "next_arrow_accessibility_text",
            "value": "Seguinte",
            "attr": {
                "priority": "translate"
            }
        },
        {
            "name": "general_copy",
            "value": "Copiar",
            "attr": {
                "priority": "translate"
            }
        },
        {
            "name": "general_start",
            "value": "Iniciar",
            "attr": {
                "priority": "translate"
            }
        },
        {
            "name": "general_more",
            "value": "Mais",
            "attr": {
                "priority": "translate"
            }
        },
        {
            "name": "navigation_back",
            "value": "Anterior",
            "attr": {
                "priority": "translate"
            }
        },
        {
            "name": "general_cancel",
            "value": "Cancelar",
            "attr": {
                "priority": "translate"
            }
        },
        {
            "name": "general_display_lunar_calendar",
            "value": "Mostrar calendário lunar",
            "attr": {
                "priority": "translate"
            }
        },
        {
            "name": "sheet_close",
            "value": "Fechar",
            "attr": {
                "priority": "translate"
            }
        },
        {
            "name": "general_select_all",
            "value": "Selecionar tudo",
            "attr": {
                "priority": "translate"
            }
        },
        {
            "name": "stepper_back",
            "value": "Anterior",
            "attr": {
                "priority": "translate"
            }
        },
        {
            "name": "general_cut",
            "value": "Cortar",
            "attr": {
                "priority": "translate"
            }
        },
        {
            "name": "general_confirm",
            "value": "OK",
            "attr": {
                "priority": "translate"
            }
        },
        {
            "name": "general_skip",
            "value": "Ignorar",
            "attr": {
                "priority": "translate"
            }
        },
        {
            "name": "last_updated_time",
            "value": "Última atualização: %s",
            "attr": {
                "priority": "translate"
            }
        },
        {
            "name": "general_close",
            "value": "Desativado",
            "attr": {
                "priority": "translate"
            }
        },
        {
            "name": "general_paste",
            "value": "Colar",
            "attr": {
                "priority": "translate"
            }
        },
        {
            "name": "general_open",
            "value": "Ativado",
            "attr": {
                "priority": "translate"
            }
        },
        {
            "name": "stepper_next",
            "value": "Seguinte",
            "attr": {
                "priority": "translate"
            }
        }
    ]
}
